NebulaPythonSDK/__init__.py
NebulaPythonSDK/sdk.py
NebulaPythonSDK-2.8.0.data/scripts/setup.py
test/__init__.py
test/test_nebula_python_sdk.py
NebulaPythonSDK-2.8.0.dist-info/LICENSE
NebulaPythonSDK-2.8.0.dist-info/METADATA
NebulaPythonSDK-2.8.0.dist-info/WHEEL
NebulaPythonSDK-2.8.0.dist-info/top_level.txt
NebulaPythonSDK-2.8.0.dist-info/RECORD
