Metadata-Version: 2.1
Name: NebulaPythonSDK
Version: 2.8.0
Summary: NebulaPythonSDK is a Pythonic SDK to manage Nebula container orchestrator
Home-page: https://github.com/nebula-orchestrator/nebula-python-sdk
Author: Naor Livne
Author-email: naorlivne@gmail.com
License: LGPLv3
Keywords: nebula container orchestrator sdk
Platform: UNKNOWN
Classifier: Development Status :: 5 - Production/Stable
Classifier: Environment :: Other Environment
Classifier: License :: OSI Approved :: GNU Lesser General Public License v3 (LGPLv3)
Classifier: Operating System :: OS Independent
Classifier: Intended Audience :: Developers
Classifier: Intended Audience :: System Administrators
Classifier: Topic :: Internet :: WWW/HTTP
Classifier: Topic :: Software Development :: Libraries :: Python Modules
Classifier: Programming Language :: Python
Classifier: Programming Language :: Python :: 3
Classifier: Programming Language :: Python :: 3.4
Classifier: Programming Language :: Python :: 3.5
Classifier: Programming Language :: Python :: 3.6
Classifier: Programming Language :: Python :: 3.7
Classifier: Programming Language :: Python :: 3.8
Requires-Dist: requests (>=2.3.0)
Requires-Dist: six (>=1.12.0)
